resi/__init__.py
resi/cover_letter.py
resi/open_ai_writer.py
resi/resume.py
resi/template.py
resi/utils/__init__.py
resi/utils/pdf_utils.py
resi/utils/word_utils.py
resi_builder-1.2.0.dist-info/licenses/LICENSE
resi_builder-1.2.0.dist-info/METADATA
resi_builder-1.2.0.dist-info/WHEEL
resi_builder-1.2.0.dist-info/top_level.txt
resi_builder-1.2.0.dist-info/RECORD
