Metadata-Version: 2.4
Name: resi-builder
Version: 1.2.0
Summary: Create a resume and cover letter automatically
Home-page: https://github.com/cerdamario13/resi-builder
Author: Mario Cerda
Author-email: cerdamario13@gmail.com
Requires-Python: >=3.10
License-File: LICENSE
Dynamic: author
Dynamic: author-email
Dynamic: description
Dynamic: description-content-type
Dynamic: home-page
Dynamic: license-file
Dynamic: requires-python
Dynamic: summary
